toolbox_geohash-0.1.0-py3.6-nspkg.pth
toolbox/geohash/__init__.py
toolbox/geohash/lib/__init__.py
toolbox/geohash/lib/icosahedron.py
toolbox/geohash/lib/point.py
toolbox/geohash/lib/ray.py
toolbox/geohash/lib/sphere_approx.py
toolbox/geohash/lib/tetrahedron.py
toolbox/geohash/lib/tri.py
toolbox/geohash/lib/util.py
toolbox_geohash-0.1.0.dist-info/DESCRIPTION.rst
toolbox_geohash-0.1.0.dist-info/METADATA
toolbox_geohash-0.1.0.dist-info/RECORD
toolbox_geohash-0.1.0.dist-info/WHEEL
toolbox_geohash-0.1.0.dist-info/metadata.json
toolbox_geohash-0.1.0.dist-info/namespace_packages.txt
toolbox_geohash-0.1.0.dist-info/top_level.txt
