Metadata-Version: 2.0
Name: toolbox-geohash
Version: 0.1.0
Summary: Module to encode any coordinate on earth to an integer and back to coordinates.
Requires-Dist: numpy
